roland/__init__.py
roland/abundance.py
roland/atmos.py
roland/atmosphere.py
roland/atomic.py
roland/hofermodels.py
roland/korg.py
roland/kuruczgrid.py
roland/linelist.py
roland/marcsgrid.py
roland/models.py
roland/spectrumizer.py
roland/utils.py
roland/atmos/asun.dat
roland/atmos/avega.dat
roland/atmos/kurucz_data.txt.gz
roland/atmos/kurucz_index.fits
roland/atmos/marcs_data.txt.gz
roland/atmos/marcs_index.fits
roland/atmos/periodic_table.txt
roland-1.0.0.dist-info/LICENSE
roland-1.0.0.dist-info/METADATA
roland-1.0.0.dist-info/WHEEL
roland-1.0.0.dist-info/top_level.txt
roland-1.0.0.dist-info/RECORD
